snakemake_executor_plugin_slurm/__init__.py
snakemake_executor_plugin_slurm/efficiency_report.py
snakemake_executor_plugin_slurm/job_status_query.py
snakemake_executor_plugin_slurm/partitions.py
snakemake_executor_plugin_slurm/submit_string.py
snakemake_executor_plugin_slurm/utils.py
snakemake_executor_plugin_slurm/validation.py
snakemake_executor_plugin_slurm-2.0.3.dist-info/METADATA
snakemake_executor_plugin_slurm-2.0.3.dist-info/WHEEL
snakemake_executor_plugin_slurm-2.0.3.dist-info/licenses/LICENSE
snakemake_executor_plugin_slurm-2.0.3.dist-info/RECORD
